swagou/__init__.py
swagou/cli.py
swagou/filter.py
swagou_cli-0.1.0.dist-info/licenses/LICENSE
swagou_cli-0.1.0.dist-info/METADATA
swagou_cli-0.1.0.dist-info/WHEEL
swagou_cli-0.1.0.dist-info/entry_points.txt
swagou_cli-0.1.0.dist-info/top_level.txt
swagou_cli-0.1.0.dist-info/RECORD
