Metadata-Version: 2.4
Name: swagou-cli
Version: 0.1.0
Summary: Swagger Opinionated utilities for filtering OpenAPI specifications
Author: Malik Sulaimanov
License: MIT
Classifier: Programming Language :: Python :: 3
Classifier: License :: OSI Approved :: MIT License
Classifier: Operating System :: OS Independent
Requires-Python: >=3.11
License-File: LICENSE
Requires-Dist: typer>=0.15.3
Requires-Dist: httpx>=0.25.0
Requires-Dist: pyyaml>=6.0.0
Requires-Dist: rich
Provides-Extra: dev
Requires-Dist: pytest>=7.0.0; extra == "dev"
Requires-Dist: black>=23.0.0; extra == "dev"
Requires-Dist: isort>=5.0.0; extra == "dev"
Requires-Dist: mypy>=1.0.0; extra == "dev"
Dynamic: license-file
